napari_pointslayer_projection/__init__.py
napari_pointslayer_projection/_version.py
napari_pointslayer_projection/_widget.py
napari_pointslayer_projection/napari.yaml
napari_pointslayer_projection/_tests/__init__.py
napari_pointslayer_projection/_tests/test_widget.py
napari_pointslayer_projection-0.0.2.dist-info/LICENSE
napari_pointslayer_projection-0.0.2.dist-info/METADATA
napari_pointslayer_projection-0.0.2.dist-info/WHEEL
napari_pointslayer_projection-0.0.2.dist-info/entry_points.txt
napari_pointslayer_projection-0.0.2.dist-info/top_level.txt
napari_pointslayer_projection-0.0.2.dist-info/RECORD
