Metadata-Version: 2.1
Name: napari-pointslayer-projection
Version: 0.0.2
Summary: This plugin creates a 2d projection of all your points.
Home-page: https://github.com/gatoniel/napari-pointslayer-projection
Author: Niklas Netter
Author-email: niknett@gmail.com
License: BSD-3-Clause
Project-URL: Bug Tracker, https://github.com/gatoniel/napari-pointslayer-projection/issues
Project-URL: Documentation, https://github.com/gatoniel/napari-pointslayer-projection#README.md
Project-URL: Source Code, https://github.com/gatoniel/napari-pointslayer-projection
Project-URL: User Support, https://github.com/gatoniel/napari-pointslayer-projection/issues
Classifier: Development Status :: 2 - Pre-Alpha
Classifier: Framework :: napari
Classifier: Intended Audience :: Developers
Classifier: License :: OSI Approved :: BSD License
Classifier: Operating System :: OS Independent
Classifier: Programming Language :: Python
Classifier: Programming Language :: Python :: 3
Classifier: Programming Language :: Python :: 3 :: Only
Classifier: Programming Language :: Python :: 3.8
Classifier: Programming Language :: Python :: 3.9
Classifier: Programming Language :: Python :: 3.10
Classifier: Topic :: Scientific/Engineering :: Image Processing
Requires-Python: >=3.8
License-File: LICENSE
Requires-Dist: numpy
Requires-Dist: magicgui
Requires-Dist: qtpy
Provides-Extra: testing
Requires-Dist: tox ; extra == 'testing'
Requires-Dist: pytest ; extra == 'testing'
Requires-Dist: pytest-cov ; extra == 'testing'
Requires-Dist: pytest-qt ; extra == 'testing'
Requires-Dist: napari ; extra == 'testing'
Requires-Dist: pyqt5 ; extra == 'testing'
